MANIFEST.in
README.md
setup.cfg
setup.py
mc3020/__init__.py
mc3020/__main__.py
mc3020/mc3020.py
mc3020/arc/frag_util.arc
mc3020/arc/m.bridge.arc
mc3020/arc/m.class.arc
mc3020/arc/m.component.arc
mc3020/arc/m.datatype.arc
mc3020/arc/m.domain.arc
mc3020/arc/m.event.arc
mc3020/arc/m.system.arc
mc3020/arc/model.mc3020_meta.arc
mc3020/arc/q.class.arc
mc3020/arc/q.class.cdispatch.arc
mc3020/arc/q.class.events.arc
mc3020/arc/q.class.factory.arc
mc3020/arc/q.class.instance.dumper.arc
mc3020/arc/q.class.link.arc
mc3020/arc/q.class.pei.arc
mc3020/arc/q.class.persist.arc
mc3020/arc/q.class.poly.arc
mc3020/arc/q.class.sem.arc
mc3020/arc/q.class.sm_sm.arc
mc3020/arc/q.class.where.arc
mc3020/arc/q.classes.arc
mc3020/arc/q.datatype.arc
mc3020/arc/q.domain.analyze.arc
mc3020/arc/q.domain.bridge.arc
mc3020/arc/q.domain.bridges.arc
mc3020/arc/q.domain.classes.arc
mc3020/arc/q.domain.datatype.arc
mc3020/arc/q.domain.limits.arc
mc3020/arc/q.domain.sync.arc
mc3020/arc/q.main.arc
mc3020/arc/q.names.arc
mc3020/arc/q.oal.act_blk.arc
mc3020/arc/q.oal.action.arc
mc3020/arc/q.oal.analyze.arc
mc3020/arc/q.oal.test.arc
mc3020/arc/q.oal.translate.arc
mc3020/arc/q.oal.utils.arc
mc3020/arc/q.parameters.arc
mc3020/arc/q.parm.sort.arc
mc3020/arc/q.r_rel.arc
mc3020/arc/q.rel.pseudoformalize.arc
mc3020/arc/q.smt.generate.arc
mc3020/arc/q.sys.populate.arc
mc3020/arc/q.utils.arc
mc3020/arc/q.val.translate.arc
mc3020/arc/readme.txt
mc3020/arc/sys_util.arc
mc3020/arc/t.class.attribute.init.c
mc3020/arc/t.class.attribute.mda.c
mc3020/arc/t.class.attribute.mda.h
mc3020/arc/t.class.cdispatch.c
mc3020/arc/t.class.cdispatch.h
mc3020/arc/t.class.event.h
mc3020/arc/t.class.extent.c
mc3020/arc/t.class.extent.h
mc3020/arc/t.class.idispatch.c
mc3020/arc/t.class.idispatch.h
mc3020/arc/t.class.instancedumper.c
mc3020/arc/t.class.instancedumper.h
mc3020/arc/t.class.link.h
mc3020/arc/t.class.op.c
mc3020/arc/t.class.ops.c
mc3020/arc/t.class.relate_assoc.c
mc3020/arc/t.class.relate_assoc.h
pymc3020.egg-info/PKG-INFO
pymc3020.egg-info/SOURCES.txt
pymc3020.egg-info/dependency_links.txt
pymc3020.egg-info/not-zip-safe
pymc3020.egg-info/requires.txt
pymc3020.egg-info/top_level.txt