Metadata-Version: 2.1
Name: pymc3020
Version: 1.0.4
Summary: Python executor for MC-3020
Home-page: https://github.com/xtuml/mc
Author: Levi Starrett
Author-email: levi@roxsoftware.com
License: Apache 2.0
Download-URL: https://github.com/xtuml/mc/releases/download/1.0.4/pymc3020-1.0.4.tar.gz
Keywords: xtuml bridgepoint
Platform: UNKNOWN
